screenrecord/__init__.py
screenrecord/__main__.py
screenrecord/cli.py
screenrecord/srecord.py
screenrecord-1.1.3.dist-info/licenses/LICENSE
screenrecord-1.1.3.dist-info/METADATA
screenrecord-1.1.3.dist-info/WHEEL
screenrecord-1.1.3.dist-info/entry_points.txt
screenrecord-1.1.3.dist-info/top_level.txt
screenrecord-1.1.3.dist-info/RECORD
