Metadata-Version: 2.4
Name: screenrecord
Version: 1.1.3
Summary: Record screen with python
Author: Sukhbinder Singh
License: Apache-2.0
Project-URL: Homepage, https://github.com/sukhbinder/screenrecord
Project-URL: Changelog, https://github.com/sukhbinder/screenrecord/releases
Project-URL: Issues, https://github.com/sukhbinder/screenrecord/issues
Project-URL: CI, https://github.com/sukhbinder/screenrecord/actions
Classifier: License :: OSI Approved :: Apache Software License
Requires-Python: >=3.8
License-File: LICENSE
Requires-Dist: imageio
Requires-Dist: pillow
Requires-Dist: imageio-ffmpeg
Requires-Dist: Quartz; sys_platform != "win32"
Provides-Extra: test
Requires-Dist: pytest; extra == "test"
Dynamic: license-file
